setup.py
gravatar_plus/__init__.py
gravatar_plus/gravatar_plus.py
pelican_gravatar_plus.egg-info/PKG-INFO
pelican_gravatar_plus.egg-info/SOURCES.txt
pelican_gravatar_plus.egg-info/dependency_links.txt
pelican_gravatar_plus.egg-info/requires.txt
pelican_gravatar_plus.egg-info/top_level.txt