Metadata-Version: 1.0
Name: pelican-gravatar-plus
Version: 0.0.1
Summary: Pelican Plugin to pull Gravtars
Home-page: https://bitbucket.org/redmonkey/pelican-plugin-gravatar-plus
Author: Michele Memoli
Author-email: michele@100shapes.com
License: UNKNOWN
Platform: any
Classifier: Development Status :: 4 - Beta
Classifier: Intended Audience :: Developers
Classifier: License :: OSI Approved :: BSD License
Classifier: Operating System :: OS Independent
Classifier: Programming Language :: Python
